{
    "DNDConfig": null,
    "__parentReadjusting__": false,
    "_height_": {
        "type": "string",
        "value": "100%"
    },
    "_left_": {
        "type": "string",
        "value": "-0.03%"
    },
    "_margin_": [
        0,
        0,
        0,
        0
    ],
    "_orientation_": 6,
    "_padding_": [
        0,
        0,
        0,
        0
    ],
    "_percent_": true,
    "_skin_": "s7fe636da62147a6ab429c18678e169e",
    "_top_": {
        "type": "string",
        "value": "0dp"
    },
    "_width_": {
        "type": "string",
        "value": "100%"
    },
    "allboxes": [],
    "autogrowmode": 0,
    "canUpdateUI": true,
    "children": [
        "lblSignupMessage",
        "imgProfilePic",
        "btnUploadPhoto",
        "tbxName",
        "tbxCustId",
        "tbxMobNo",
        "tbxEmailId",
        "tbxNationId"
    ],
    "clipbounds": true,
    "containerweight": 100,
    "enablescrolling": true,
    "id": "flxSignupDetails",
    "info": null,
    "iscustomlayout": false,
    "isvisible": true,
    "kuid": "d86b29f1228345a78eac2f526c5c6036",
    "layouttype": 4,
    "name": "kony.ui.FlexContainer",
    "parent": "flxInner2",
    "pf": "frmLogin",
    "retaincontentalignment": false,
    "retainflexpositionproperties": false,
    "retainflowhorizontalalignment": false,
    "snapgridsize": 10,
    "snaptogrid": true,
    "wType": "FlexContainer",
    "widgetalignment": 1,
    "zindex": 1
}