{
    "@class": "com.kony.gen.viz.model.component.KVizImage2",
    "DNDConfig": null,
    "__parentReadjusting__": false,
    "_base64_": null,
    "_height_": {
        "type": "string",
        "value": "170dp"
    },
    "_left_": {
        "type": "string",
        "value": "-37dp"
    },
    "_margin_": [
        0,
        0,
        0,
        0
    ],
    "_padding_": [
        0,
        0,
        0,
        0
    ],
    "_skin_": "se5594be41174e689b9fe7e9f9cc2b87",
    "_src_": "user_photo.png",
    "_top_": {
        "type": "string",
        "value": "-27dp"
    },
    "_width_": {
        "type": "string",
        "value": "130dp"
    },
    "canUpdateUI": true,
    "containerweight": 100,
    "context": {
        "channel": "mobile",
        "formID": "frmDashboard",
        "platform": "android",
        "templateType": "forms",
        "topLevelBox": null
    },
    "id": "imgUserPicture",
    "imagescalemode": 0,
    "info": null,
    "invokedProperty": "src",
    "iscustomlayout": false,
    "isvisible": true,
    "kuid": "d16051ef5c8e47408b4d70e33dd6efef",
    "name": "kony.ui.Image2",
    "parent": "flxUserPicture",
    "pf": "frmDashboard",
    "retaincontentalignment": false,
    "retainflexpositionproperties": false,
    "srcType": 1,
    "wType": "Image",
    "widgetalignment": 5,
    "zindex": 1
}